nbqol/__init__.py
nbqol/cli.py
nbqol/devices.py
nbqol/options.py
nbqol/env/__init__.py
nbqol/env/detect.py
nbqol/env/pathutils.py
nbqol/outputs/__init__.py
nbqol/outputs/capture.py
nbqol/process/__init__.py
nbqol/process/analyze.py
nbqol/process/reformat.py
nbqol/styles/__init__.py
nbqol/styles/options.py
nbqol/styles/css/vscode.css
nbqol/stylizer/__init__.py
nbqol/stylizer/auto_style.py
nbqol-0.1.1.dist-info/METADATA
nbqol-0.1.1.dist-info/WHEEL
nbqol-0.1.1.dist-info/entry_points.txt
nbqol-0.1.1.dist-info/licenses/LICENSE
nbqol-0.1.1.dist-info/RECORD
