Metadata-Version: 2.4
Name: nbqol
Version: 0.1.1
Summary: Cross-platform, modular, quality-of-life tool kit for working with Jupyter notebooks
Project-URL: Homepage, https://github.com/colinconwell/NB-QOL
Project-URL: Documentation, https://colinconwell.github.io/NB-QOL/
Author-email: Colin Conwell <colinconwell@gmail.com>
License: GPL-3.0-or-later
License-File: LICENSE
Keywords: gpu,ipython,jupyter,notebook,utility
Classifier: Development Status :: 4 - Beta
Classifier: Intended Audience :: Developers
Classifier: Intended Audience :: Science/Research
Classifier: License :: OSI Approved :: GNU General Public License v3 or later (GPLv3+)
Classifier: Programming Language :: Python :: 3
Classifier: Programming Language :: Python :: 3.9
Classifier: Topic :: Scientific/Engineering
Classifier: Topic :: Software Development :: Libraries :: Python Modules
Requires-Python: >=3.9
Requires-Dist: ipython>=7.34.0
Requires-Dist: nbconvert>=7.1.0
Requires-Dist: nbformat>=5.7.0
Requires-Dist: numpy>=1.24.3
Requires-Dist: pandas>=1.5.3
Provides-Extra: dev
Requires-Dist: black>=23.0.0; extra == 'dev'
Requires-Dist: pytest>=7.0.0; extra == 'dev'
Provides-Extra: docs
Requires-Dist: myst-parser>=2.0.0; extra == 'docs'
Requires-Dist: sphinx-autobuild>=2021.3.14; extra == 'docs'
Requires-Dist: sphinx>=7.0.0; extra == 'docs'
Requires-Dist: sphinxawesome-theme>=4.0.0; extra == 'docs'
